ABOUT.txt
CHANGES.txt
COPYRIGHT.txt
LICENSE.txt
README.txt
base.cfg
index.txt
setup.py
doc/about.txt
doc/conf.py
doc/modules.txt
doc/unittests.txt
tl/__init__.py
tl.rename.egg-info/PKG-INFO
tl.rename.egg-info/SOURCES.txt
tl.rename.egg-info/dependency_links.txt
tl.rename.egg-info/entry_points.txt
tl.rename.egg-info/namespace_packages.txt
tl.rename.egg-info/not-zip-safe
tl.rename.egg-info/requires.txt
tl.rename.egg-info/top_level.txt
tl/rename/__init__.py
tl/rename/case.py
tl/rename/case.txt
tl/rename/cli.py
tl/rename/core.py
tl/rename/core.txt
tl/rename/interactive.py
tl/rename/replace.py
tl/rename/replace.txt
tl/rename/tests.py