Metadata-Version: 1.0
Name: tl.rename
Version: 0.1.2
Summary: A rename implementation that does more than substring replacement.
Home-page: http://packages.python.org/tl.rename/
Author: Thomas Lotze
Author-email: thomas@thomas-lotze.de
License: ZPL 2.1
Keywords: rename files
Platform: UNKNOWN
Classifier: Development Status :: 3 - Alpha
Classifier: Environment :: Console
Classifier: Intended Audience :: End Users/Desktop
Classifier: License :: OSI Approved :: Zope Public License
Classifier: Natural Language :: English
Classifier: Operating System :: POSIX
